eko/__init__.py
eko/basis_rotation.py
eko/beta.py
eko/constants.py
eko/couplings.py
eko/evolution_operator/__init__.py
eko/evolution_operator/__init__.py.patch
eko/evolution_operator/flavors.py
eko/evolution_operator/matching_condition.py
eko/evolution_operator/operator_matrix_element.py
eko/evolution_operator/operator_matrix_element.py.patch
eko/evolution_operator/physical.py
eko/evolution_operator/quad_ker.py
eko/gamma.py
eko/interpolation.py
eko/io/__init__.py
eko/io/access.py
eko/io/dictlike.py
eko/io/exceptions.py
eko/io/inventory.py
eko/io/items.py
eko/io/manipulate.py
eko/io/metadata.py
eko/io/paths.py
eko/io/raw.py
eko/io/runcards.py
eko/io/struct.py
eko/io/types.py
eko/io/v1.py
eko/io/v2.py
eko/kernels/__init__.py
eko/kernels/as4_evolution_integrals.py
eko/kernels/evolution_integrals.py
eko/kernels/non_singlet.py
eko/kernels/non_singlet_qed.py
eko/kernels/singlet.py
eko/kernels/singlet_qed.py
eko/kernels/valence_qed.py
eko/matchings.py
eko/mellin.py
eko/member.py
eko/msbar_masses.py
eko/quantities/__init__.py
eko/quantities/couplings.py
eko/quantities/heavy_quarks.py
eko/runner/__init__.py
eko/runner/commons.py
eko/runner/managed.py
eko/runner/operators.py
eko/runner/parts.py
eko/runner/recipes.py
eko/scale_variations/__init__.py
eko/scale_variations/expanded.py
eko/scale_variations/exponentiated.py
eko/version.py
ekobox/__init__.py
ekobox/apply.py
ekobox/cards.py
ekobox/cli/__init__.py
ekobox/cli/base.py
ekobox/cli/inspect.py
ekobox/cli/library.py
ekobox/cli/log.py
ekobox/cli/run.py
ekobox/cli/runcards.py
ekobox/evol_pdf.py
ekobox/genpdf/Toy.info
ekobox/genpdf/__init__.py
ekobox/genpdf/cli.py
ekobox/genpdf/export.py
ekobox/genpdf/flavors.py
ekobox/genpdf/load.py
ekobox/genpdf/templatePDF.info
ekobox/info_file.py
ekobox/mock.py
ekobox/utils.py
ekobox/version.py
ekomark/__init__.py
ekomark/benchmark/__init__.py
ekomark/benchmark/external/LHA.yaml
ekomark/benchmark/external/LHA_polarized.yaml
ekomark/benchmark/external/LHA_utils.py
eko-0.15.2.dist-info/LICENSE
eko-0.15.2.dist-info/METADATA
eko-0.15.2.dist-info/WHEEL
eko-0.15.2.dist-info/entry_points.txt
eko-0.15.2.dist-info/RECORD
