Metadata-Version: 2.3
Name: eko
Version: 0.15.2
Summary: Evolution Kernel Operators
Author: A. Barontini
Author-email: andrea.barontini@mi.infn.it
Requires-Python: >=3.9,<3.14
Classifier: License :: OSI Approved :: GNU General Public License v3 (GPLv3)
Classifier: Programming Language :: Python
Classifier: Programming Language :: Python :: 3
Classifier: Programming Language :: Python :: 3.9
Classifier: Programming Language :: Python :: 3.10
Classifier: Programming Language :: Python :: 3.11
Classifier: Programming Language :: Python :: 3.12
Classifier: Programming Language :: Python :: 3.13
Classifier: Topic :: Scientific/Engineering
Classifier: Topic :: Scientific/Engineering :: Physics
Provides-Extra: box
Provides-Extra: mark
Requires-Dist: PyYAML (>=6.0,<7.0)
Requires-Dist: banana-hep (>=0.6.16,<0.7.0) ; extra == "mark"
Requires-Dist: click (>=8.0.3,<9.0.0) ; extra == "box"
Requires-Dist: lz4 (>=4.0.2,<5.0.0)
Requires-Dist: matplotlib (>=3.5.1,<4.0.0) ; extra == "mark"
Requires-Dist: numba (>=0.60.0,<0.62.0)
Requires-Dist: numpy (>=2,<3)
Requires-Dist: packaging (>=24.1,<25.0)
Requires-Dist: pandas (>=2.1.4,<3.0.0) ; extra == "mark"
Requires-Dist: rich (>=12.6.0,<13.0.0) ; extra == "box"
Requires-Dist: scipy (>=1.10.1,<2.0.0)
Requires-Dist: sqlalchemy (>=1.4.21,<2.0.0) ; extra == "mark"
Project-URL: Repository, https://github.com/NNPDF/eko
